Fibonacci/fibonacci_tester.v
/* 
Material Circuitos Digitales 2

Archivo: fibonacci_tester.v 

Descripcion: Este archivo contiene el tester de un sumador.
Aqui se realizan las pruebas, en este caso, nuestras salidas en el DUT van a ser nuestras entradas, y
nuestras entradas en el DUT seran nuestras salidas. 

Autor: Ing. Ana Eugenia Sanchez Villalobos
*/

`timescale 1ns/1ns // Escala de tiempo

module fibonacci_tester (
    output reg clk   ,
    output reg rst   ,
    output reg enb   ,
    input [11:0] fibout
);


// Definiendo el clk
always begin 
    #5 clk = !clk; 
end

initial begin
    clk = 0;
    enb = 1;
end

initial begin
    rst = 1;
    #15;

    rst = 0;
    #100;

    $finish;
end


endmodule

Fibonacci/fibonacci.v
/* 
Material Circuitos Digitales 2

Archivo: fibonacci.v 

Descripcion: Este archivo contiene el DUT de un sumador.

Autor: Ing. Ana Eugenia Sanchez Villalobos
*/


module fibonacci (
    input clk   ,
    input rst   ,
    input enb   ,
    output [11:0] fibout
);

reg [11:0] valor_previo;
reg [11:0] valor_actual;

always @(posedge clk) begin
    if(enb) begin
        if(!rst) begin
            valor_previo <= valor_actual; 
            valor_actual <= valor_actual + valor_previo;
    end else begin // Volver a iniciar
            valor_previo <= 0;
            valor_actual <= 1;
    end
    end
end

assign fibout = valor_previo;
    
endmodule

Fibonacci/fibonacci_testbench.v
/* 
Material Circuitos Digitales 2

Archivo: fibonacci_tester.v

Descripcion: Testbench del sumador.


    ----------                  -----------
    |           |               |         |
    |   TEST    | <---------->  |   DUT   |
    |           |               |         |
    ----------                  ----------

Autor: Ing. Ana Eugenia Sanchez Villalobos
*/

`include "fibonacci.v"
`include "fibonacci_tester.v" 


module fibonacci_testbench;
    wire clk   ;
    wire rst   ;
    wire enb   ;
    wire [11:0] fibout;


    fibonacci DUT(
        .clk(clk),
        .rst(rst), 
        .enb(enb), 
        .fibout(fibout[11:0])
    );

    // Instantiate the tester module
    fibonacci_tester test(
        .clk(clk),
        .rst(rst), 
        .enb(enb), 
        .fibout(fibout[11:0])
    );

    /* Para generar las ondas y
    y visualizar en gtkwave
    */
    initial begin
        $dumpfile("tb.vcd");
        $dumpvars;
    end

    //Mostrar los valores
    always @(posedge clk) begin
        if(!rst) begin
            $display("Valor de Fibonacci: %b", fibout);
        end
    end

endmodule

Fibonacci/tb.vcd
$date
	Mon Jan  8 20:18:54 2024
$end
$version
	Icarus Verilog
$end
$timescale
	1ns
$end
$scope module fibonacci_testbench $end
$var wire 1 ! rst $end
$var wire 12 " fibout [11:0] $end
$var wire 1 # enb $end
$var wire 1 $ clk $end
$scope module DUT $end
$var wire 12 % fibout [11:0] $end
$var wire 1 ! rst $end
$var wire 1 # enb $end
$var wire 1 $ clk $end
$var reg 12 & valor_actual [11:0] $end
$var reg 12 ' valor_previo [11:0] $end
$upscope $end
$scope module test $end
$var wire 12 ( fibout [11:0] $end
$var reg 1 $ clk $end
$var reg 1 # enb $end
$var reg 1 ! rst $end
$upscope $end
$upscope $end
$enddefinitions $end
#0
$dumpvars
bx (
bx '
bx &
bx %
0$
1#
bx "
1!
$end
#5
b1 &
b0 "
b0 %
b0 (
b0 '
1$
#10
0$
#15
b1 "
b1 %
b1 (
b1 '
1$
0!
#20
0$
#25
b10 &
1$
#30
0$
#35
b11 &
b10 "
b10 %
b10 (
b10 '
1$
#40
0$
#45
b101 &
b11 "
b11 %
b11 (
b11 '
1$
#50
0$
#55
b1000 &
b101 "
b101 %
b101 (
b101 '
1$
#60
0$
#65
b1101 &
b1000 "
b1000 %
b1000 (
b1000 '
1$
#70
0$
#75
b10101 &
b1101 "
b1101 %
b1101 (
b1101 '
1$
#80
0$
#85
b100010 &
b10101 "
b10101 %
b10101 (
b10101 '
1$
#90
0$
#95
b110111 &
b100010 "
b100010 %
b100010 (
b100010 '
1$
#100
0$
#105
b1011001 &
b110111 "
b110111 %
b110111 (
b110111 '
1$
#110
0$
#115
b10010000 &
b1011001 "
b1011001 %
b1011001 (
b1011001 '
1$
